consoleutil/__init__.py
consoleutil/consoleutil.py
consoleutil-0.0.1.dist-info/LICENSE
consoleutil-0.0.1.dist-info/METADATA
consoleutil-0.0.1.dist-info/WHEEL
consoleutil-0.0.1.dist-info/top_level.txt
consoleutil-0.0.1.dist-info/RECORD
