Metadata-Version: 2.1
Name: consoleutil
Version: 0.0.1
Summary: Make colored texts, bold, and console functions with color
Home-page: https://github.com/pypa/sampleproject
Author: psvks
Author-email: brofbot@gmail.com
Project-URL: Bug Tracker, https://github.com/pypa/sampleproject/issues
Classifier: Programming Language :: Python :: 3
Classifier: License :: OSI Approved :: MIT License
Classifier: Operating System :: OS Independent
Requires-Python: >=3.6
License-File: LICENSE
